opender_interface/__init__.py
opender_interface/der_interface.py
opender_interface/dx_tool_interface.py
opender_interface/opendss_interface.py
opender_interface/time_plots.py
opender_interface/voltage_regulator.py
opender_interface/xy_plot.py
opender_interface/xyplot.mplstyle
opender_interface_direct-0.1.0.dist-info/licenses/LICENSE.txt
opender_interface_direct-0.1.0.dist-info/METADATA
opender_interface_direct-0.1.0.dist-info/WHEEL
opender_interface_direct-0.1.0.dist-info/top_level.txt
opender_interface_direct-0.1.0.dist-info/RECORD
