Metadata-Version: 2.4
Name: opender-interface-direct
Version: 0.1.0
Summary: An modif. version of opender_interface to use opendssdirect.py as a opendss calc engine.
Author: Yiwei Ma, Paulo Radatz, Wei Ren
Author-email: yma@epri.com, pradatz@epri.com, wren@epric.om
Requires-Python: >=3.11
License-File: LICENSE.txt
Requires-Dist: opender==2.2.0
Requires-Dist: opendssdirect-py==0.9.4
Dynamic: author
Dynamic: author-email
Dynamic: license-file
Dynamic: requires-python
